definable/llms/__init__.py
definable/llms/__main__.py
definable/llms/config.py
definable/llms/api/__init__.py
definable/llms/api/__main__.py
definable/llms/api/main.py
definable/llms/api/middleware/__init__.py
definable/llms/api/middleware/auth.py
definable/llms/api/middleware/rate_limit.py
definable/llms/api/routes/__init__.py
definable/llms/api/routes/chat.py
definable/llms/api/routes/files.py
definable/llms/api/routes/health.py
definable/llms/api/routes/providers.py
definable/llms/api/routes/research.py
definable/llms/api/routes/sessions.py
definable/llms/base/__init__.py
definable/llms/base/exceptions.py
definable/llms/base/provider.py
definable/llms/base/types.py
definable/llms/cache/__init__.py
definable/llms/cache/redis_cache.py
definable/llms/database/__init__.py
definable/llms/database/analytics.py
definable/llms/database/backend_model_loader.py
definable/llms/database/model_loader.py
definable/llms/database/models.py
definable/llms/database/operations.py
definable/llms/database/redis_model_loader.py
definable/llms/database/schema.py
definable/llms/processors/__init__.py
definable/llms/processors/base.py
definable/llms/processors/document.py
definable/llms/processors/image.py
definable/llms/providers/__init__.py
definable/llms/providers/factory.py
definable/llms/providers/anthropic/__init__.py
definable/llms/providers/anthropic/client.py
definable/llms/providers/deepseek/__init__.py
definable/llms/providers/deepseek/client.py
definable/llms/providers/gemini/__init__.py
definable/llms/providers/gemini/client.py
definable/llms/providers/moonshot/__init__.py
definable/llms/providers/moonshot/client.py
definable/llms/providers/openai/__init__.py
definable/llms/providers/openai/client.py
definable/llms/providers/xAI/__init__.py
definable/llms/providers/xAI/client.py
definable/llms/research/__init__.py
definable/llms/research/types.py
definable/llms/research/extraction/quote_extractor.py
definable/llms/research/orchestrator/research_orchestrator.py
definable_llms-0.1.11.dist-info/METADATA
definable_llms-0.1.11.dist-info/WHEEL
definable_llms-0.1.11.dist-info/licenses/LICENSE
definable_llms-0.1.11.dist-info/RECORD
