Metadata-Version: 2.4
Name: definable-llms
Version: 0.1.11
Summary: Scalable multi-provider LLM library with unified interface for OpenAI, Gemini, Anthropic, Deepseek, Moonshot and xAI
Project-URL: Homepage, https://definable.ai
Project-URL: Repository, https://github.com/definable-ai/llms-lib
Project-URL: Documentation, https://github.com/definable-ai/llms-lib#readme
Project-URL: Issues, https://github.com/definable-ai/llms-lib/issues
Author-email: "Definable.ai Team" <info@definable.ai>
Maintainer-email: "Definable.ai Team" <info@definable.ai>
License: MIT
License-File: LICENSE
Keywords: ai,anthropic,api,chatbot,gemini,kimi,llm,moonshot,openai,xAI
Classifier: Development Status :: 4 - Beta
Classifier: Intended Audience :: Developers
Classifier: License :: OSI Approved :: MIT License
Classifier: Operating System :: OS Independent
Classifier: Programming Language :: Python :: 3
Classifier: Programming Language :: Python :: 3.10
Classifier: Programming Language :: Python :: 3.11
Classifier: Programming Language :: Python :: 3.12
Classifier: Topic :: Internet :: WWW/HTTP :: Dynamic Content
Classifier: Topic :: Scientific/Engineering :: Artificial Intelligence
Classifier: Topic :: Software Development :: Libraries :: Python Modules
Requires-Python: >=3.10
Requires-Dist: aiofiles>=24.1.0
Requires-Dist: aiohttp>=3.11.0
Requires-Dist: alembic>=1.16.5
Requires-Dist: anthropic>=0.36.0
Requires-Dist: asyncpg>=0.30.0
Requires-Dist: google-genai>=1.43.0
Requires-Dist: greenlet>=3.0.0
Requires-Dist: httpx>=0.28.0
Requires-Dist: openai>=1.68.0
Requires-Dist: openpyxl>=3.1.5
Requires-Dist: pillow>=10.4.0
Requires-Dist: psycopg2-binary>=2.9.0
Requires-Dist: pydantic-settings>=2.7.0
Requires-Dist: pydantic>=2.10.0
Requires-Dist: pypdf>=4.3.1
Requires-Dist: python-docx>=1.1.2
Requires-Dist: python-dotenv>=1.0.1
Requires-Dist: redis[hiredis]>=5.1.1
Requires-Dist: sqlalchemy>=2.0.43
Requires-Dist: structlog>=24.4.0
Requires-Dist: tenacity>=9.0.0
Requires-Dist: tiktoken>=0.8.0
Requires-Dist: xai-sdk>=1.4.1
Provides-Extra: api
Requires-Dist: fastapi[standard]>=0.116.1; extra == 'api'
Requires-Dist: python-multipart>=0.0.9; extra == 'api'
Provides-Extra: dev
Requires-Dist: mypy>=1.18.2; extra == 'dev'
Requires-Dist: pytest-asyncio>=0.21.0; extra == 'dev'
Requires-Dist: pytest-cov>=4.0.0; extra == 'dev'
Requires-Dist: pytest>=7.0.0; extra == 'dev'
Requires-Dist: ruff>=0.13.2; extra == 'dev'
Provides-Extra: research
Requires-Dist: exa-py>=1.0.0; extra == 'research'
